frogr/.DS_Store
frogr/__init__.py
frogr/__main__.py
frogr/data/.DS_Store
frogr/data/chem/chem_dummy.ncdf
frogr/data/chem/coeff9_NASA_sc.dat
frogr/data/chem/coeff_NASA_mb.dat
frogr/data/chem/coeff_NASA_sc.dat
frogr/data/chem/general_input.in
frogr/io.py
frogr/py.typed
frogr/runner.py
frogr/taurex/.DS_Store
frogr/taurex/__init__.py
frogr/util.py
frogr-0.0.2.dist-info/LICENSE
frogr-0.0.2.dist-info/WHEEL
frogr-0.0.2.dist-info/entry_points.txt
frogr-0.0.2.dist-info/METADATA
frogr-0.0.2.dist-info/RECORD
