Metadata-Version: 2.1
Name: frogr
Version: 0.0.2
Summary: ATMOpy
Home-page: https://github.com/michellebieger/atmopy
License: GPL-3.0
Author: M. F. Bieger
Author-email: mb987@exeter.ac.uk
Requires-Python: >=3.8,<4.0
Classifier: Development Status :: 1 - Planning
Classifier: License :: OSI Approved :: GNU General Public License v3 (GPLv3)
Classifier: Programming Language :: Python :: 3
Classifier: Programming Language :: Python :: 3.8
Classifier: Programming Language :: Python :: 3.9
Classifier: Programming Language :: Python :: 3.10
Classifier: Programming Language :: Python :: 3.11
Requires-Dist: astropy (>=5.1.1,<6.0.0)
Requires-Dist: ipywidgets (>=8.0.4,<9.0.0)
Requires-Dist: matplotlib (>=3.7.1,<4.0.0)
Requires-Dist: scipy (>=1.9.3,<2.0.0)
Requires-Dist: taurex (>=3.1.1a0,<4.0.0)
Requires-Dist: twine (>=4.0.2,<5.0.0)
Project-URL: Changelog, https://github.com/michellebieger/atmopy/releases
Project-URL: Documentation, https://atmopy.readthedocs.io
Project-URL: Repository, https://github.com/michellebieger/atmopy
